[
    {
        "key": "dbln",
        "value": "%7B%2261590572499811%22%3A%225Hl7eyjF%22%7D",
        "domain": "facebook.com",
        "path": "/login/device-based/",
        "hostOnly": false,
        "creation": "2026-06-22T01:16:05.203Z",
        "lastAccessed": "2026-06-22T01:16:05.204Z"
    },
    {
        "key": "datr",
        "value": "G2cyaqejjs5mmtZMfiIfQIMw",
        "domain": "facebook.com",
        "path": "/",
        "hostOnly": false,
        "creation": "2026-06-22T01:16:05.204Z",
        "lastAccessed": "2026-06-22T01:16:05.204Z"
    },
    {
        "key": "sb",
        "value": "G2cyaoEHvMrXEXwndT43geWx",
        "domain": "facebook.com",
        "path": "/",
        "hostOnly": false,
        "creation": "2026-06-22T01:16:05.204Z",
        "lastAccessed": "2026-06-22T01:16:05.204Z"
    },
    {
        "key": "ps_l",
        "value": "1",
        "domain": "facebook.com",
        "path": "/",
        "hostOnly": false,
        "creation": "2026-06-22T01:16:05.204Z",
        "lastAccessed": "2026-06-22T01:16:05.204Z"
    },
    {
        "key": "ps_n",
        "value": "1",
        "domain": "facebook.com",
        "path": "/",
        "hostOnly": false,
        "creation": "2026-06-22T01:16:05.204Z",
        "lastAccessed": "2026-06-22T01:16:05.204Z"
    },
    {
        "key": "dpr",
        "value": "2.549999952316284",
        "domain": "facebook.com",
        "path": "/",
        "hostOnly": false,
        "creation": "2026-06-22T01:16:05.204Z",
        "lastAccessed": "2026-06-22T01:16:05.204Z"
    },
    {
        "key": "locale",
        "value": "en_GB",
        "domain": "facebook.com",
        "path": "/",
        "hostOnly": false,
        "creation": "2026-06-22T01:16:05.204Z",
        "lastAccessed": "2026-06-22T01:16:05.204Z"
    },
    {
        "key": "vpd",
        "value": "v1%3B822x424x2.549999952316284",
        "domain": "facebook.com",
        "path": "/",
        "hostOnly": false,
        "creation": "2026-06-22T01:16:05.204Z",
        "lastAccessed": "2026-06-22T01:16:05.204Z"
    },
    {
        "key": "pas",
        "value": "61590572499811%3AzafvvgNnwr",
        "domain": "facebook.com",
        "path": "/",
        "hostOnly": false,
        "creation": "2026-06-22T01:16:05.204Z",
        "lastAccessed": "2026-06-22T01:16:05.204Z"
    },
    {
        "key": "wd",
        "value": "424x822",
        "domain": "facebook.com",
        "path": "/",
        "hostOnly": false,
        "creation": "2026-06-22T01:16:05.204Z",
        "lastAccessed": "2026-06-22T01:16:05.204Z"
    },
    {
        "key": "c_user",
        "value": "61590572499811",
        "domain": "facebook.com",
        "path": "/",
        "hostOnly": false,
        "creation": "2026-06-22T01:16:05.204Z",
        "lastAccessed": "2026-06-22T01:16:05.204Z"
    },
    {
        "key": "fbl_st",
        "value": "100433017%3BT%3A29701515",
        "domain": "facebook.com",
        "path": "/",
        "hostOnly": false,
        "creation": "2026-06-22T01:16:05.204Z",
        "lastAccessed": "2026-06-22T01:16:05.204Z"
    },
    {
        "key": "fr",
        "value": "1t75yOZL2K6VNIPmE.AWedxozT6Ekb0YMM3IwxpyrnMe4LF00AvAH2WnpuWXggMnmlAAo.BqOIy8..AAA.0.0.BqOIy8.AWfP8J5bvyJecel38xp7nO_RvBs",
        "domain": "facebook.com",
        "path": "/",
        "hostOnly": false,
        "creation": "2026-06-22T01:16:05.204Z",
        "lastAccessed": "2026-06-22T01:16:05.204Z"
    },
    {
        "key": "xs",
        "value": "6%3Aa6Xw0W6ewmpRtQ%3A2%3A1782090937%3A-1%3A-1%3A%3AAcyiNRvYrbIMBsVvj0jyaLz1MAE_qrHWf1-yob8yLw",
        "domain": "facebook.com",
        "path": "/",
        "hostOnly": false,
        "creation": "2026-06-22T01:16:05.204Z",
        "lastAccessed": "2026-06-22T01:16:05.204Z"
    },
    {
        "key": "wl_cbv",
        "value": "v2%3Bclient_version%3A3195%3Btimestamp%3A1782090940",
        "domain": "facebook.com",
        "path": "/",
        "hostOnly": false,
        "creation": "2026-06-22T01:16:05.204Z",
        "lastAccessed": "2026-06-22T01:16:05.204Z"
    }
]
